setup.py
DiskAlertSDK/__init__.py
DiskAlertSDK/admin.py
DiskAlertSDK/connect.py
DiskAlertSDK/disk_helper.py
DiskAlertSDK/entity.py
DiskAlertSDK/host.py
DiskAlertSDK/root.py
DiskAlertSDK/user.py
DiskAlertSDK.egg-info/PKG-INFO
DiskAlertSDK.egg-info/SOURCES.txt
DiskAlertSDK.egg-info/dependency_links.txt
DiskAlertSDK.egg-info/requires.txt
DiskAlertSDK.egg-info/top_level.txt